<annotation verified="yes">
	<folder>Annotation</folder>
	<filename>09ed54b36eaa5316.jpg</filename>
	<path>vzdy_se_meni</path>
	<source>
		<databaze>jen_uft8_symboly</databaze>
	</source>
	<size>
		<width>576</width>
		<height>1024</height>
		<depth>3</depth>
	</size>
	<segmented>0</segmented>
	<object>
		<name>apple</name>
		<pose>Unspecified</pose>
		<truncated>0</truncated>
		<difficult>0</difficult>
		<bndbox>
			<xmin>320.0</xmin>
			<ymin>241.92</ymin>
			<xmax>478.72</xmax>
			<ymax>405.75974399999996</ymax>
		</bndbox>
	</object>
	<object>
		<name>apple</name>
		<pose>Unspecified</pose>
		<truncated>0</truncated>
		<difficult>0</difficult>
		<bndbox>
			<xmin>504.32</xmin>
			<ymin>210.56025599999998</ymin>
			<xmax>723.2</xmax>
			<ymax>415.35993599999995</ymax>
		</bndbox>
	</object>
</annotation>