<annotation verified="yes">
	<folder>Annotation</folder>
	<filename>365977cd5795f7eb.jpg</filename>
	<path>vzdy_se_meni</path>
	<source>
		<databaze>jen_uft8_symboly</databaze>
	</source>
	<size>
		<width>768</width>
		<height>1024</height>
		<depth>3</depth>
	</size>
	<segmented>0</segmented>
	<object>
		<name>apple</name>
		<pose>Unspecified</pose>
		<truncated>0</truncated>
		<difficult>0</difficult>
		<bndbox>
			<xmin>389.76</xmin>
			<ymin>33.279744</ymin>
			<xmax>672.64</xmax>
			<ymax>353.28000000000003</ymax>
		</bndbox>
	</object>
	<object>
		<name>apple</name>
		<pose>Unspecified</pose>
		<truncated>0</truncated>
		<difficult>0</difficult>
		<bndbox>
			<xmin>69.76</xmin>
			<ymin>0.0</ymin>
			<xmax>1023.36</xmax>
			<ymax>574.08</ymax>
		</bndbox>
	</object>
</annotation>