<annotation verified="yes">
	<folder>Annotation</folder>
	<filename>48518075399ab662.jpg</filename>
	<path>vzdy_se_meni</path>
	<source>
		<databaze>jen_uft8_symboly</databaze>
	</source>
	<size>
		<width>1024</width>
		<height>768</height>
		<depth>3</depth>
	</size>
	<segmented>0</segmented>
	<object>
		<name>apple</name>
		<pose>Unspecified</pose>
		<truncated>0</truncated>
		<difficult>0</difficult>
		<bndbox>
			<xmin>343.68</xmin>
			<ymin>778.24</ymin>
			<xmax>464.00025600000004</xmax>
			<ymax>887.68</ymax>
		</bndbox>
	</object>
	<object>
		<name>apple</name>
		<pose>Unspecified</pose>
		<truncated>0</truncated>
		<difficult>0</difficult>
		<bndbox>
			<xmin>67.19999999999999</xmin>
			<ymin>202.24</ymin>
			<xmax>431.36025600000005</xmax>
			<ymax>344.32</ymax>
		</bndbox>
	</object>
	<object>
		<name>apple</name>
		<pose>Unspecified</pose>
		<truncated>0</truncated>
		<difficult>0</difficult>
		<bndbox>
			<xmin>78.08025599999999</xmin>
			<ymin>662.4</ymin>
			<xmax>93.440256</xmax>
			<ymax>702.72</ymax>
		</bndbox>
	</object>
	<object>
		<name>apple</name>
		<pose>Unspecified</pose>
		<truncated>0</truncated>
		<difficult>0</difficult>
		<bndbox>
			<xmin>79.35974399999999</xmin>
			<ymin>497.92</ymin>
			<xmax>95.36025599999999</xmax>
			<ymax>529.28</ymax>
		</bndbox>
	</object>
	<object>
		<name>apple</name>
		<pose>Unspecified</pose>
		<truncated>0</truncated>
		<difficult>0</difficult>
		<bndbox>
			<xmin>83.199744</xmin>
			<ymin>529.28</ymin>
			<xmax>97.28025600000001</xmax>
			<ymax>547.2</ymax>
		</bndbox>
	</object>
	<object>
		<name>apple</name>
		<pose>Unspecified</pose>
		<truncated>0</truncated>
		<difficult>0</difficult>
		<bndbox>
			<xmin>83.199744</xmin>
			<ymin>90.24</ymin>
			<xmax>394.23974400000003</xmax>
			<ymax>211.2</ymax>
		</bndbox>
	</object>
	<object>
		<name>apple</name>
		<pose>Unspecified</pose>
		<truncated>0</truncated>
		<difficult>0</difficult>
		<bndbox>
			<xmin>86.4</xmin>
			<ymin>707.84</ymin>
			<xmax>95.36025599999999</xmax>
			<ymax>732.16</ymax>
		</bndbox>
	</object>
	<object>
		<name>apple</name>
		<pose>Unspecified</pose>
		<truncated>0</truncated>
		<difficult>0</difficult>
		<bndbox>
			<xmin>95.36025599999999</xmin>
			<ymin>25.6</ymin>
			<xmax>158.079744</xmax>
			<ymax>94.08</ymax>
		</bndbox>
	</object>
	<object>
		<name>apple</name>
		<pose>Unspecified</pose>
		<truncated>0</truncated>
		<difficult>0</difficult>
		<bndbox>
			<xmin>97.28025600000001</xmin>
			<ymin>833.92</ymin>
			<xmax>114.560256</xmax>
			<ymax>876.16</ymax>
		</bndbox>
	</object>
	<object>
		<name>apple</name>
		<pose>Unspecified</pose>
		<truncated>0</truncated>
		<difficult>0</difficult>
		<bndbox>
			<xmin>97.28025600000001</xmin>
			<ymin>896.64</ymin>
			<xmax>124.80000000000001</xmax>
			<ymax>949.12</ymax>
		</bndbox>
	</object>
	<object>
		<name>apple</name>
		<pose>Unspecified</pose>
		<truncated>0</truncated>
		<difficult>0</difficult>
		<bndbox>
			<xmin>112.640256</xmin>
			<ymin>342.4</ymin>
			<xmax>334.719744</xmax>
			<ymax>609.92</ymax>
		</bndbox>
	</object>
	<object>
		<name>apple</name>
		<pose>Unspecified</pose>
		<truncated>0</truncated>
		<difficult>0</difficult>
		<bndbox>
			<xmin>114.560256</xmin>
			<ymin>952.96</ymin>
			<xmax>144.639744</xmax>
			<ymax>984.32</ymax>
		</bndbox>
	</object>
	<object>
		<name>apple</name>
		<pose>Unspecified</pose>
		<truncated>0</truncated>
		<difficult>0</difficult>
		<bndbox>
			<xmin>177.279744</xmin>
			<ymin>624.0</ymin>
			<xmax>426.24</xmax>
			<ymax>888.32</ymax>
		</bndbox>
	</object>
	<object>
		<name>apple</name>
		<pose>Unspecified</pose>
		<truncated>0</truncated>
		<difficult>0</difficult>
		<bndbox>
			<xmin>217.599744</xmin>
			<ymin>961.28</ymin>
			<xmax>394.23974400000003</xmax>
			<ymax>1023.36</ymax>
		</bndbox>
	</object>
	<object>
		<name>apple</name>
		<pose>Unspecified</pose>
		<truncated>0</truncated>
		<difficult>0</difficult>
		<bndbox>
			<xmin>275.199744</xmin>
			<ymin>10.88</ymin>
			<xmax>324.48</xmax>
			<ymax>42.88</ymax>
		</bndbox>
	</object>
	<object>
		<name>apple</name>
		<pose>Unspecified</pose>
		<truncated>0</truncated>
		<difficult>0</difficult>
		<bndbox>
			<xmin>326.4</xmin>
			<ymin>391.04</ymin>
			<xmax>408.320256</xmax>
			<ymax>528.0</ymax>
		</bndbox>
	</object>
	<object>
		<name>apple</name>
		<pose>Unspecified</pose>
		<truncated>0</truncated>
		<difficult>0</difficult>
		<bndbox>
			<xmin>343.68</xmin>
			<ymin>48.0</ymin>
			<xmax>350.720256</xmax>
			<ymax>62.08</ymax>
		</bndbox>
	</object>
	<object>
		<name>apple</name>
		<pose>Unspecified</pose>
		<truncated>0</truncated>
		<difficult>0</difficult>
		<bndbox>
			<xmin>380.79974400000003</xmin>
			<ymin>977.28</ymin>
			<xmax>476.799744</xmax>
			<ymax>1023.36</ymax>
		</bndbox>
	</object>
	<object>
		<name>apple</name>
		<pose>Unspecified</pose>
		<truncated>0</truncated>
		<difficult>0</difficult>
		<bndbox>
			<xmin>397.43999999999994</xmin>
			<ymin>0.0</ymin>
			<xmax>425.60025599999994</xmax>
			<ymax>16.64</ymax>
		</bndbox>
	</object>
	<object>
		<name>apple</name>
		<pose>Unspecified</pose>
		<truncated>0</truncated>
		<difficult>0</difficult>
		<bndbox>
			<xmin>411.519744</xmin>
			<ymin>69.76</ymin>
			<xmax>416.64</xmax>
			<ymax>76.8</ymax>
		</bndbox>
	</object>
	<object>
		<name>apple</name>
		<pose>Unspecified</pose>
		<truncated>0</truncated>
		<difficult>0</difficult>
		<bndbox>
			<xmin>416.64</xmin>
			<ymin>71.68</ymin>
			<xmax>423.680256</xmax>
			<ymax>82.56</ymax>
		</bndbox>
	</object>
	<object>
		<name>apple</name>
		<pose>Unspecified</pose>
		<truncated>0</truncated>
		<difficult>0</difficult>
		<bndbox>
			<xmin>418.56000000000006</xmin>
			<ymin>3.84</ymin>
			<xmax>436.479744</xmax>
			<ymax>17.92</ymax>
		</bndbox>
	</object>
	<object>
		<name>apple</name>
		<pose>Unspecified</pose>
		<truncated>0</truncated>
		<difficult>0</difficult>
		<bndbox>
			<xmin>424.32</xmin>
			<ymin>291.84</ymin>
			<xmax>767.360256</xmax>
			<ymax>604.8</ymax>
		</bndbox>
	</object>
	<object>
		<name>apple</name>
		<pose>Unspecified</pose>
		<truncated>0</truncated>
		<difficult>0</difficult>
		<bndbox>
			<xmin>426.24</xmin>
			<ymin>578.56</ymin>
			<xmax>767.360256</xmax>
			<ymax>840.96</ymax>
		</bndbox>
	</object>
	<object>
		<name>apple</name>
		<pose>Unspecified</pose>
		<truncated>0</truncated>
		<difficult>0</difficult>
		<bndbox>
			<xmin>427.520256</xmin>
			<ymin>80.64</ymin>
			<xmax>434.559744</xmax>
			<ymax>97.92</ymax>
		</bndbox>
	</object>
	<object>
		<name>apple</name>
		<pose>Unspecified</pose>
		<truncated>0</truncated>
		<difficult>0</difficult>
		<bndbox>
			<xmin>432.63974399999995</xmin>
			<ymin>92.8</ymin>
			<xmax>446.72025600000006</xmax>
			<ymax>103.04</ymax>
		</bndbox>
	</object>
	<object>
		<name>apple</name>
		<pose>Unspecified</pose>
		<truncated>0</truncated>
		<difficult>0</difficult>
		<bndbox>
			<xmin>522.24</xmin>
			<ymin>910.72</ymin>
			<xmax>625.280256</xmax>
			<ymax>974.08</ymax>
		</bndbox>
	</object>
	<object>
		<name>apple</name>
		<pose>Unspecified</pose>
		<truncated>0</truncated>
		<difficult>0</difficult>
		<bndbox>
			<xmin>534.399744</xmin>
			<ymin>119.68</ymin>
			<xmax>546.560256</xmax>
			<ymax>133.76</ymax>
		</bndbox>
	</object>
	<object>
		<name>apple</name>
		<pose>Unspecified</pose>
		<truncated>0</truncated>
		<difficult>0</difficult>
		<bndbox>
			<xmin>534.399744</xmin>
			<ymin>131.84</ymin>
			<xmax>546.560256</xmax>
			<ymax>142.08</ymax>
		</bndbox>
	</object>
	<object>
		<name>apple</name>
		<pose>Unspecified</pose>
		<truncated>0</truncated>
		<difficult>0</difficult>
		<bndbox>
			<xmin>546.560256</xmin>
			<ymin>44.16</ymin>
			<xmax>742.400256</xmax>
			<ymax>112.64</ymax>
		</bndbox>
	</object>
	<object>
		<name>apple</name>
		<pose>Unspecified</pose>
		<truncated>0</truncated>
		<difficult>0</difficult>
		<bndbox>
			<xmin>556.8</xmin>
			<ymin>135.04</ymin>
			<xmax>568.959744</xmax>
			<ymax>149.12</ymax>
		</bndbox>
	</object>
	<object>
		<name>apple</name>
		<pose>Unspecified</pose>
		<truncated>0</truncated>
		<difficult>0</difficult>
		<bndbox>
			<xmin>576.639744</xmin>
			<ymin>956.16</ymin>
			<xmax>730.239744</xmax>
			<ymax>1023.36</ymax>
		</bndbox>
	</object>
	<object>
		<name>apple</name>
		<pose>Unspecified</pose>
		<truncated>0</truncated>
		<difficult>0</difficult>
		<bndbox>
			<xmin>595.839744</xmin>
			<ymin>853.12</ymin>
			<xmax>698.88</xmax>
			<ymax>963.2</ymax>
		</bndbox>
	</object>
	<object>
		<name>apple</name>
		<pose>Unspecified</pose>
		<truncated>0</truncated>
		<difficult>0</difficult>
		<bndbox>
			<xmin>618.24</xmin>
			<ymin>169.6</ymin>
			<xmax>640.640256</xmax>
			<ymax>200.96</ymax>
		</bndbox>
	</object>
	<object>
		<name>apple</name>
		<pose>Unspecified</pose>
		<truncated>0</truncated>
		<difficult>0</difficult>
		<bndbox>
			<xmin>647.679744</xmin>
			<ymin>185.6</ymin>
			<xmax>658.5600000000001</xmax>
			<ymax>199.68</ymax>
		</bndbox>
	</object>
	<object>
		<name>apple</name>
		<pose>Unspecified</pose>
		<truncated>0</truncated>
		<difficult>0</difficult>
		<bndbox>
			<xmin>651.519744</xmin>
			<ymin>190.72</ymin>
			<xmax>668.7997439999999</xmax>
			<ymax>209.92</ymax>
		</bndbox>
	</object>
	<object>
		<name>apple</name>
		<pose>Unspecified</pose>
		<truncated>0</truncated>
		<difficult>0</difficult>
		<bndbox>
			<xmin>656.64</xmin>
			<ymin>848.0</ymin>
			<xmax>767.360256</xmax>
			<ymax>1001.6</ymax>
		</bndbox>
	</object>
	<object>
		<name>apple</name>
		<pose>Unspecified</pose>
		<truncated>0</truncated>
		<difficult>0</difficult>
		<bndbox>
			<xmin>669.440256</xmin>
			<ymin>165.76</ymin>
			<xmax>760.3199999999999</xmax>
			<ymax>258.56</ymax>
		</bndbox>
	</object>
</annotation>