<annotation verified="yes">
	<folder>Annotation</folder>
	<filename>58627eb62e385214.jpg</filename>
	<path>vzdy_se_meni</path>
	<source>
		<databaze>jen_uft8_symboly</databaze>
	</source>
	<size>
		<width>683</width>
		<height>1024</height>
		<depth>3</depth>
	</size>
	<segmented>0</segmented>
	<object>
		<name>apple</name>
		<pose>Unspecified</pose>
		<truncated>0</truncated>
		<difficult>0</difficult>
		<bndbox>
			<xmin>650.24</xmin>
			<ymin>158.896535</ymin>
			<xmax>720.0</xmax>
			<ymax>229.375305</ymax>
		</bndbox>
	</object>
	<object>
		<name>apple</name>
		<pose>Unspecified</pose>
		<truncated>0</truncated>
		<difficult>0</difficult>
		<bndbox>
			<xmin>175.36</xmin>
			<ymin>425.43318700000003</ymin>
			<xmax>216.32</xmax>
			<ymax>461.95387999999997</ymax>
		</bndbox>
	</object>
	<object>
		<name>apple</name>
		<pose>Unspecified</pose>
		<truncated>0</truncated>
		<difficult>0</difficult>
		<bndbox>
			<xmin>294.4</xmin>
			<ymin>601.629429</ymin>
			<xmax>333.44</xmax>
			<ymax>641.994729</ymax>
		</bndbox>
	</object>
	<object>
		<name>apple</name>
		<pose>Unspecified</pose>
		<truncated>0</truncated>
		<difficult>0</difficult>
		<bndbox>
			<xmin>329.6</xmin>
			<ymin>449.139434</ymin>
			<xmax>375.68</xmax>
			<ymax>491.42669600000005</ymax>
		</bndbox>
	</object>
	<object>
		<name>apple</name>
		<pose>Unspecified</pose>
		<truncated>0</truncated>
		<difficult>0</difficult>
		<bndbox>
			<xmin>330.88</xmin>
			<ymin>509.367057</ymin>
			<xmax>366.08</xmax>
			<ymax>551.653636</ymax>
		</bndbox>
	</object>
	<object>
		<name>apple</name>
		<pose>Unspecified</pose>
		<truncated>0</truncated>
		<difficult>0</difficult>
		<bndbox>
			<xmin>426.88</xmin>
			<ymin>349.18853099999995</ymin>
			<xmax>462.08</xmax>
			<ymax>383.787262</ymax>
		</bndbox>
	</object>
	<object>
		<name>apple</name>
		<pose>Unspecified</pose>
		<truncated>0</truncated>
		<difficult>0</difficult>
		<bndbox>
			<xmin>428.16</xmin>
			<ymin>244.11171299999998</ymin>
			<xmax>464.64</xmax>
			<ymax>267.81796</ymax>
		</bndbox>
	</object>
	<object>
		<name>apple</name>
		<pose>Unspecified</pose>
		<truncated>0</truncated>
		<difficult>0</difficult>
		<bndbox>
			<xmin>438.4</xmin>
			<ymin>438.888287</ymin>
			<xmax>474.24</xmax>
			<ymax>495.27130300000005</ymax>
		</bndbox>
	</object>
	<object>
		<name>apple</name>
		<pose>Unspecified</pose>
		<truncated>0</truncated>
		<difficult>0</difficult>
		<bndbox>
			<xmin>443.52</xmin>
			<ymin>512.570327</ymin>
			<xmax>492.16</xmax>
			<ymax>565.108736</ymax>
		</bndbox>
	</object>
	<object>
		<name>apple</name>
		<pose>Unspecified</pose>
		<truncated>0</truncated>
		<difficult>0</difficult>
		<bndbox>
			<xmin>469.76</xmin>
			<ymin>533.073304</ymin>
			<xmax>533.12</xmax>
			<ymax>595.222206</ymax>
		</bndbox>
	</object>
	<object>
		<name>apple</name>
		<pose>Unspecified</pose>
		<truncated>0</truncated>
		<difficult>0</difficult>
		<bndbox>
			<xmin>499.2</xmin>
			<ymin>447.858126</ymin>
			<xmax>522.24</xmax>
			<ymax>467.72044900000003</ymax>
		</bndbox>
	</object>
	<object>
		<name>apple</name>
		<pose>Unspecified</pose>
		<truncated>0</truncated>
		<difficult>0</difficult>
		<bndbox>
			<xmin>506.88</xmin>
			<ymin>495.27130300000005</ymin>
			<xmax>568.32</xmax>
			<ymax>555.498243</ymax>
		</bndbox>
	</object>
	<object>
		<name>apple</name>
		<pose>Unspecified</pose>
		<truncated>0</truncated>
		<difficult>0</difficult>
		<bndbox>
			<xmin>515.84</xmin>
			<ymin>447.858126</ymin>
			<xmax>564.48</xmax>
			<ymax>488.86407999999994</ymax>
		</bndbox>
	</object>
	<object>
		<name>apple</name>
		<pose>Unspecified</pose>
		<truncated>0</truncated>
		<difficult>0</difficult>
		<bndbox>
			<xmin>523.52</xmin>
			<ymin>149.92669600000002</ymin>
			<xmax>580.48</xmax>
			<ymax>203.746413</ymax>
		</bndbox>
	</object>
	<object>
		<name>apple</name>
		<pose>Unspecified</pose>
		<truncated>0</truncated>
		<difficult>0</difficult>
		<bndbox>
			<xmin>528.0</xmin>
			<ymin>604.192045</ymin>
			<xmax>580.48</xmax>
			<ymax>639.43143</ymax>
		</bndbox>
	</object>
	<object>
		<name>apple</name>
		<pose>Unspecified</pose>
		<truncated>0</truncated>
		<difficult>0</difficult>
		<bndbox>
			<xmin>559.36</xmin>
			<ymin>178.758858</ymin>
			<xmax>602.24</xmax>
			<ymax>236.42318200000003</ymax>
		</bndbox>
	</object>
	<object>
		<name>apple</name>
		<pose>Unspecified</pose>
		<truncated>0</truncated>
		<difficult>0</difficult>
		<bndbox>
			<xmin>622.08</xmin>
			<ymin>310.10522199999997</ymin>
			<xmax>682.88</xmax>
			<ymax>379.302001</ymax>
		</bndbox>
	</object>
	<object>
		<name>apple</name>
		<pose>Unspecified</pose>
		<truncated>0</truncated>
		<difficult>0</difficult>
		<bndbox>
			<xmin>638.08</xmin>
			<ymin>207.59102</ymin>
			<xmax>698.24</xmax>
			<ymax>255.00351400000002</ymax>
		</bndbox>
	</object>
	<object>
		<name>apple</name>
		<pose>Unspecified</pose>
		<truncated>0</truncated>
		<difficult>0</difficult>
		<bndbox>
			<xmin>670.72</xmin>
			<ymin>365.206247</ymin>
			<xmax>727.04</xmax>
			<ymax>421.58926299999996</ymax>
		</bndbox>
	</object>
	<object>
		<name>apple</name>
		<pose>Unspecified</pose>
		<truncated>0</truncated>
		<difficult>0</difficult>
		<bndbox>
			<xmin>709.12</xmin>
			<ymin>541.4024890000001</ymin>
			<xmax>740.48</xmax>
			<ymax>596.503514</ymax>
		</bndbox>
	</object>
	<object>
		<name>apple</name>
		<pose>Unspecified</pose>
		<truncated>0</truncated>
		<difficult>0</difficult>
		<bndbox>
			<xmin>714.24</xmin>
			<ymin>291.524207</ymin>
			<xmax>780.8</xmax>
			<ymax>351.75114700000006</ymax>
		</bndbox>
	</object>
	<object>
		<name>apple</name>
		<pose>Unspecified</pose>
		<truncated>0</truncated>
		<difficult>0</difficult>
		<bndbox>
			<xmin>740.48</xmin>
			<ymin>547.809712</ymin>
			<xmax>784.64</xmax>
			<ymax>575.360566</ymax>
		</bndbox>
	</object>
	<object>
		<name>apple</name>
		<pose>Unspecified</pose>
		<truncated>0</truncated>
		<difficult>0</difficult>
		<bndbox>
			<xmin>758.4</xmin>
			<ymin>322.918985</ymin>
			<xmax>808.32</xmax>
			<ymax>381.223963</ymax>
		</bndbox>
	</object>
	<object>
		<name>apple</name>
		<pose>Unspecified</pose>
		<truncated>0</truncated>
		<difficult>0</difficult>
		<bndbox>
			<xmin>795.52</xmin>
			<ymin>554.216935</ymin>
			<xmax>855.68</xmax>
			<ymax>606.755344</ymax>
		</bndbox>
	</object>
	<object>
		<name>apple</name>
		<pose>Unspecified</pose>
		<truncated>0</truncated>
		<difficult>0</difficult>
		<bndbox>
			<xmin>798.08</xmin>
			<ymin>599.066813</ymin>
			<xmax>842.88</xmax>
			<ymax>640.712738</ymax>
		</bndbox>
	</object>
</annotation>