<annotation verified="yes">
	<folder>Annotation</folder>
	<filename>8947839989306e28.jpg</filename>
	<path>vzdy_se_meni</path>
	<source>
		<databaze>jen_uft8_symboly</databaze>
	</source>
	<size>
		<width>1024</width>
		<height>774</height>
		<depth>3</depth>
	</size>
	<segmented>0</segmented>
	<object>
		<name>apple</name>
		<pose>Unspecified</pose>
		<truncated>0</truncated>
		<difficult>0</difficult>
		<bndbox>
			<xmin>373</xmin>
			<ymin>525</ymin>
			<xmax>771</xmax>
			<ymax>865</ymax>
		</bndbox>
	</object>
	<object>
		<name>apple</name>
		<pose>Unspecified</pose>
		<truncated>0</truncated>
		<difficult>0</difficult>
		<bndbox>
			<xmin>56</xmin>
			<ymin>538</ymin>
			<xmax>407</xmax>
			<ymax>891</ymax>
		</bndbox>
	</object>
	<object>
		<name>apple</name>
		<pose>Unspecified</pose>
		<truncated>0</truncated>
		<difficult>0</difficult>
		<bndbox>
			<xmin>75</xmin>
			<ymin>319</ymin>
			<xmax>374</xmax>
			<ymax>595</ymax>
		</bndbox>
	</object>
	<object>
		<name>apple</name>
		<pose>Unspecified</pose>
		<truncated>0</truncated>
		<difficult>0</difficult>
		<bndbox>
			<xmin>373</xmin>
			<ymin>330</ymin>
			<xmax>635</xmax>
			<ymax>540</ymax>
		</bndbox>
	</object>
</annotation>