<annotation verified="yes">
	<folder>Annotation</folder>
	<filename>91f7f54bbfee37f7.jpg</filename>
	<path>vzdy_se_meni</path>
	<source>
		<databaze>jen_uft8_symboly</databaze>
	</source>
	<size>
		<width>1024</width>
		<height>992</height>
		<depth>3</depth>
	</size>
	<segmented>0</segmented>
	<object>
		<name>apple</name>
		<pose>Unspecified</pose>
		<truncated>0</truncated>
		<difficult>0</difficult>
		<bndbox>
			<xmin>469</xmin>
			<ymin>166</ymin>
			<xmax>717</xmax>
			<ymax>398</ymax>
		</bndbox>
	</object>
	<object>
		<name>apple</name>
		<pose>Unspecified</pose>
		<truncated>0</truncated>
		<difficult>0</difficult>
		<bndbox>
			<xmin>171</xmin>
			<ymin>355</ymin>
			<xmax>257</xmax>
			<ymax>521</ymax>
		</bndbox>
	</object>
	<object>
		<name>apple</name>
		<pose>Unspecified</pose>
		<truncated>0</truncated>
		<difficult>0</difficult>
		<bndbox>
			<xmin>667</xmin>
			<ymin>279</ymin>
			<xmax>837</xmax>
			<ymax>465</ymax>
		</bndbox>
	</object>
</annotation>