<annotation verified="yes">
	<folder>Annotation</folder>
	<filename>a9948144e2b7b4b8.jpg</filename>
	<path>vzdy_se_meni</path>
	<source>
		<databaze>jen_uft8_symboly</databaze>
	</source>
	<size>
		<width>768</width>
		<height>1024</height>
		<depth>3</depth>
	</size>
	<segmented>0</segmented>
	<object>
		<name>apple</name>
		<pose>Unspecified</pose>
		<truncated>0</truncated>
		<difficult>0</difficult>
		<bndbox>
			<xmin>139.52</xmin>
			<ymin>184.32</ymin>
			<xmax>279.04</xmax>
			<ymax>323.840256</ymax>
		</bndbox>
	</object>
	<object>
		<name>apple</name>
		<pose>Unspecified</pose>
		<truncated>0</truncated>
		<difficult>0</difficult>
		<bndbox>
			<xmin>0.0</xmin>
			<ymin>166.400256</ymin>
			<xmax>119.68</xmax>
			<ymax>321.279744</ymax>
		</bndbox>
	</object>
	<object>
		<name>apple</name>
		<pose>Unspecified</pose>
		<truncated>0</truncated>
		<difficult>0</difficult>
		<bndbox>
			<xmin>4.48</xmin>
			<ymin>383.36025600000005</ymin>
			<xmax>122.24</xmax>
			<ymax>510.72</ymax>
		</bndbox>
	</object>
	<object>
		<name>apple</name>
		<pose>Unspecified</pose>
		<truncated>0</truncated>
		<difficult>0</difficult>
		<bndbox>
			<xmin>85.12</xmin>
			<ymin>307.839744</ymin>
			<xmax>188.16</xmax>
			<ymax>407.04</ymax>
		</bndbox>
	</object>
	<object>
		<name>apple</name>
		<pose>Unspecified</pose>
		<truncated>0</truncated>
		<difficult>0</difficult>
		<bndbox>
			<xmin>119.68</xmin>
			<ymin>417.920256</ymin>
			<xmax>214.4</xmax>
			<ymax>535.6800000000001</ymax>
		</bndbox>
	</object>
	<object>
		<name>apple</name>
		<pose>Unspecified</pose>
		<truncated>0</truncated>
		<difficult>0</difficult>
		<bndbox>
			<xmin>183.04</xmin>
			<ymin>314.88</ymin>
			<xmax>304.64</xmax>
			<ymax>421.76025599999997</ymax>
		</bndbox>
	</object>
</annotation>