<annotation verified="yes">
    <folder>Annotation</folder>
    <filename>Apple%20536.jpg</filename>
    <path>vzdy_se_meni</path>
    <source>
        <database>Unknown</database>
    </source>
    <size>
        <width>320</width>
        <height>258</height>
        <depth>3</depth>
    </size>
    <segmented>0</segmented>
    <object>
    <name>apple</name>
    <pose>Unspecified</pose>
    <truncated>0</truncated>
    <difficult>0</difficult>
    <bndbox>
        <xmin>189.77115716753022</xmin>
        <ymin>109.66381156316916</ymin>
        <xmax>258.3031088082902</xmax>
        <ymax>186.4561027837259</ymax>
    </bndbox>
</object>
</annotation>