<annotation verified="yes">
    <folder>Annotation</folder>
    <filename>Apple%20246.jpg</filename>
    <path>vzdy_se_meni</path>
    <source>
        <database>Unknown</database>
    </source>
    <size>
        <width>480</width>
        <height>322</height>
        <depth>3</depth>
    </size>
    <segmented>0</segmented>
    <object>
    <name>apple</name>
    <pose>Unspecified</pose>
    <truncated>0</truncated>
    <difficult>0</difficult>
    <bndbox>
        <xmin>112.71598272138229</xmin>
        <ymin>176.89270386266094</ymin>
        <xmax>228.13714902807774</xmax>
        <ymax>279.5042918454935</ymax>
    </bndbox>
</object><object>
    <name>apple</name>
    <pose>Unspecified</pose>
    <truncated>0</truncated>
    <difficult>0</difficult>
    <bndbox>
        <xmin>133.1047516198704</xmin>
        <ymin>89.8283261802575</ymin>
        <xmax>235.39416846652267</xmax>
        <ymax>178.9656652360515</ymax>
    </bndbox>
</object><object>
    <name>apple</name>
    <pose>Unspecified</pose>
    <truncated>0</truncated>
    <difficult>0</difficult>
    <bndbox>
        <xmin>208.7850971922246</xmin>
        <ymin>31.094420600858367</ymin>
        <xmax>312.8023758099352</xmax>
        <ymax>110.21244635193133</ymax>
    </bndbox>
</object><object>
    <name>apple</name>
    <pose>Unspecified</pose>
    <truncated>0</truncated>
    <difficult>0</difficult>
    <bndbox>
        <xmin>315.91252699784013</xmin>
        <ymin>48.02360515021459</ymin>
        <xmax>431.3336933045356</xmax>
        <ymax>156.85407725321886</ymax>
    </bndbox>
</object><object>
    <name>apple</name>
    <pose>Unspecified</pose>
    <truncated>0</truncated>
    <difficult>0</difficult>
    <bndbox>
        <xmin>232.97516198704102</xmin>
        <ymin>109.5214592274678</ymin>
        <xmax>337.33801295896325</xmax>
        <ymax>205.91416309012874</ymax>
    </bndbox>
</object><object>
    <name>apple</name>
    <pose>Unspecified</pose>
    <truncated>0</truncated>
    <difficult>0</difficult>
    <bndbox>
        <xmin>334.57343412526996</xmin>
        <ymin>156.5085836909871</ymin>
        <xmax>449.3034557235421</xmax>
        <ymax>263.6115879828326</ymax>
    </bndbox>
</object><object>
    <name>apple</name>
    <pose>Unspecified</pose>
    <truncated>0</truncated>
    <difficult>0</difficult>
    <bndbox>
        <xmin>230.90172786177104</xmin>
        <ymin>205.568669527897</ymin>
        <xmax>346.3228941684665</xmax>
        <ymax>309.56223175965664</ymax>
    </bndbox>
</object>
</annotation>